<?xml version="1.0" encoding="utf-8" ?>
<Patch>


	<Operation Class="PatchOperationFindMod">
		<mods>
			<li>Giddy-up! Core</li>
		</mods>

		<match Class="PatchOperationSequence">
			<operations>




				<li Class="PatchOperationAddModExtension">
					<xpath>/Defs/ThingDef[defName = "RttR_Fury"]</xpath> 
					<value>
						<li Class="GiddyUpCore.AllowedLifeStagesPatch">
							<allowedLifeStagesCSV>RttR_AnimalAdolescent,AnimalAdult</allowedLifeStagesCSV>
							
						</li>				
					</value>
				</li>
				<li Class="PatchOperationAddModExtension">
					<xpath>/Defs/ThingDef[defName = "RttR_Flightmare"]</xpath> 
					<value>
						<li Class="GiddyUpCore.AllowedLifeStagesPatch">
							<allowedLifeStagesCSV>RttR_AnimalAdolescent,AnimalAdult</allowedLifeStagesCSV>
							
						</li>				
					</value>
				</li>
				<li Class="PatchOperationAddModExtension">
					<xpath>/Defs/ThingDef[defName = "RttR_Gronckle"]</xpath> 
					<value>
						<li Class="GiddyUpCore.AllowedLifeStagesPatch">
							<allowedLifeStagesCSV>RttR_AnimalAdolescent,AnimalAdult</allowedLifeStagesCSV>
							
						</li>				
					</value>
				</li>
				<li Class="PatchOperationAddModExtension">
					<xpath>/Defs/ThingDef[defName = "RttR_Hotburple"]</xpath> 
					<value>
						<li Class="GiddyUpCore.AllowedLifeStagesPatch">
							<allowedLifeStagesCSV>RttR_AnimalAdolescent,AnimalAdult</allowedLifeStagesCSV>
							
						</li>				
					</value>
				</li>
				<li Class="PatchOperationAddModExtension">
					<xpath>/Defs/ThingDef[defName = "RttR_Nadder"]</xpath> 
					<value>
						<li Class="GiddyUpCore.AllowedLifeStagesPatch">
							<allowedLifeStagesCSV>RttR_AnimalAdolescent,AnimalAdult</allowedLifeStagesCSV>
							
						</li>				
					</value>
				</li>
				<li Class="PatchOperationAddModExtension">
					<xpath>/Defs/ThingDef[defName = "RttR_Nightmare"]</xpath> 
					<value>
						<li Class="GiddyUpCore.AllowedLifeStagesPatch">
							<allowedLifeStagesCSV>RttR_AnimalAdolescent,AnimalAdult</allowedLifeStagesCSV>
							
						</li>				
					</value>
				</li>
				<li Class="PatchOperationAddModExtension">
					<xpath>/Defs/ThingDef[defName = "RttR_Scauldron"]</xpath> 
					<value>
						<li Class="GiddyUpCore.AllowedLifeStagesPatch">
							<allowedLifeStagesCSV>RttR_AnimalAdolescent,AnimalAdult</allowedLifeStagesCSV>
							
						</li>				
					</value>
				</li>
				<li Class="PatchOperationAddModExtension">
					<xpath>/Defs/ThingDef[defName = "RttR_Zippleback"]</xpath> 
					<value>
						<li Class="GiddyUpCore.AllowedLifeStagesPatch">
							<allowedLifeStagesCSV>RttR_AnimalAdolescent,AnimalAdult</allowedLifeStagesCSV>
							
						</li>				
					</value>
				</li>
			
				
				<li Class="PatchOperationAddModExtension">
					<xpath>/Defs/ThingDef[defName = "RttR_Fury"]</xpath> 
					<value>
						<li Class="GiddyUpCore.DrawingOffsetPatch">
							<eastOffsetCSV>0.77,0,0.14</eastOffsetCSV>
							<westOffsetCSV>-0.77,0,0.14</westOffsetCSV>
							<northOffsetCSV>0,0,0.14</northOffsetCSV>
							<southOffsetCSV>0,0,-0.24</southOffsetCSV>
						</li>				
					</value>
				</li>
				
				<li Class="PatchOperationAddModExtension">
					<xpath>/Defs/ThingDef[defName = "RttR_Gronckle"]</xpath> 
					<value>
						<li Class="GiddyUpCore.DrawingOffsetPatch">
							<eastOffsetCSV>0.148,0,-0.348</eastOffsetCSV>
							<westOffsetCSV>-0.148,0,-0.348</westOffsetCSV>
							<northOffsetCSV>0,0,-0.348</northOffsetCSV>
							<southOffsetCSV>0,0,-0.348</southOffsetCSV>
						</li>				
					</value>
				</li>


			</operations>
		</match>
	</Operation>


</Patch>

